{
  "display": {
    "icon": {
      "item": "minecraft:mossy_stone_bricks"
    },
    "title": "And we begin...",
    "description": "Start a muffinhunt by punching an osfan",
    "background": "minecraft:warped_planks",
    "frame": "task",
    "show_toast": true,
    "announce_to_chat": true,
    "hidden": false
  },
  "criteria": {
    "requirement": {
      "trigger": "minecraft:player_hurt_entity",
      "conditions": {
        "player": {
          "type": "minecraft:player",
          "team": "juggernaut"
        },
        "entity": [
          {
            "condition": "minecraft:entity_properties",
            "entity": "this",
            "predicate": {
              "type": "minecraft:player",
              "team": "dragon_ender"
            }
          }
        ]
      }
    }
  },
  "rewards": {
    "function": "muffinhunt:begin_overworld",
    "experience": 50
  }
}
